og_log/__init__.py
og_log/callbacks.py
og_log/formatter.py
og_log/level.py
og_log/log.py
og_log/callback/console.py
og_log/callback/file.py
og_log/callback/network.py
og_log-0.3.2.dist-info/licenses/LICENSE
og_log-0.3.2.dist-info/METADATA
og_log-0.3.2.dist-info/WHEEL
og_log-0.3.2.dist-info/top_level.txt
og_log-0.3.2.dist-info/RECORD
