Metadata-Version: 2.4
Name: og-log
Version: 0.3.2
Summary: Simple logger
Author-email: Olivier Galand <galand.olivier.david@gmail.com>
Maintainer-email: Olivier Galand <galand.olivier.david@gmail.com>
License:                     GNU GENERAL PUBLIC LICENSE
Project-URL: Homepage, https://github.com/OlivierGaland/pyog-log
Keywords: development
Classifier: Development Status :: 3 - Alpha
Classifier: Intended Audience :: Developers
Classifier: Topic :: Software Development :: Debuggers
Classifier: License :: OSI Approved :: GNU General Public License v3 (GPLv3)
Classifier: Programming Language :: Python :: 3
Classifier: Programming Language :: Python :: 3.7
Classifier: Programming Language :: Python :: 3.8
Classifier: Programming Language :: Python :: 3.9
Classifier: Programming Language :: Python :: 3.10
Classifier: Programming Language :: Python :: 3.11
Classifier: Programming Language :: Python :: 3 :: Only
Requires-Python: >=3.7
License-File: LICENSE
Dynamic: license-file
